setup.py
coinsuper/__init__.py
coinsuper/rest/__init__.py
coinsuper/rest/cns_api.py
coinsuper/rest/coinsuper_constant.py
coinsuper/rest/coinsuper_rest.py
coinsuper/rest/coinsuper_rest_sandbox_test.py
coinsuper/rest/coinsuper_util.py
coinsuper/rest/error/__init__.py
coinsuper/rest/error/coinsuper_rest_error.py
coinsuper/rest/logger/__init__.py
coinsuper/rest/logger/coinsuper_simple_log.py
coinsuper/rest/vo/__init__.py
coinsuper/rest/vo/external/__init__.py
coinsuper/rest/vo/external/req_bo.py
coinsuper/rest/vo/internal/__init__.py
coinsuper/rest/vo/internal/req_bo.py
coinsuper/rest/vo/internal/resp_bo.py
coinsuper_api_rest_sdk.egg-info/PKG-INFO
coinsuper_api_rest_sdk.egg-info/SOURCES.txt
coinsuper_api_rest_sdk.egg-info/dependency_links.txt
coinsuper_api_rest_sdk.egg-info/top_level.txt