Metadata-Version: 1.0
Name: coinsuper-api-rest-sdk
Version: 0.0.3
Summary: Coinsuper API REST SDK
Home-page: https://github.com/coinsuperapi/coinsuper-api-rest-python-sdk
Author: coinsuperapi
Author-email: UNKNOWN
License: Coinsuper
Keywords: pip,coinsuper,exchange,api,sdk
Platform: any
